nlpa/__init__.py
nlpa-0.1.0.dist-info/LICENSE.txt
nlpa-0.1.0.dist-info/METADATA
nlpa-0.1.0.dist-info/WHEEL
nlpa-0.1.0.dist-info/top_level.txt
nlpa-0.1.0.dist-info/RECORD
