Metadata-Version: 2.1
Name: nlpa
Version: 0.1.0
Summary: A very basic nlp automation
Home-page: https://github.com/nerds-coding/nlpa
Author: Anup Prakash
Author-email: 2000.anupprakash@gmail.com
License: MIT
Keywords: nlp automation
Platform: UNKNOWN
Classifier: Development Status :: 5 - Production/Stable
Classifier: Intended Audience :: Education
Classifier: License :: OSI Approved :: MIT License
Classifier: Programming Language :: Python :: 3
Requires-Python: >=3
Requires-Dist: pandas
Requires-Dist: numpy
Requires-Dist: nltk
Requires-Dist: contractions
Requires-Dist: emoji
